{"directed": false, "multigraph": false, "graph": {}, "nodes": [{"comments": [{"source": "Morning Post, December 14, 1940, 26", "content": "MC"}], "legal_names": [{"source": "Troy NY Times Record, July 23, 1935, 9", "content": "Alfred Carman"}, {"source": "Cohoes American, July 24, 1935, page unknown", "content": "Alfred Carmen"}, {"source": "Knickerbocker Press, July 24, 1935, page unknown", "content": "Alfred Carmen"}, {"source": "Schenectady NY Gazette, July 24, 1935, 16", "content": "Alfred Carman"}, {"source": "Albany NY Times-Union, July 27, 1935, 4", "content": "Alfred Carmen"}, {"source": "Cohoes American, July 27, 1935, page unknown", "content": "Alfred Carmen"}, {"source": "Troy NY Times Record, July 27, 1935, 7", "content": "Alfred Carmen"}, {"source": "Saratogian, August 22, 1935, 10", "content": "Alfred Carmen"}, {"source": "Troy NY Times Record, August 22, 1935, page unknown", "content": "Alfred Carmen"}, {"source": "Miami Herald, March 24, 1939, C1", "content": "Alfred Carmen"}], "alleged_ages": [{"source": "Troy NY Times Record, July 23, 1935, 9", "content": 34.0}, {"source": "Cohoes American, July 24, 1935, page unknown", "content": 34.0}, {"source": "Knickerbocker Press, July 24, 1935, page unknown", "content": 34.0}, {"source": "Albany NY Times-Union, July 27, 1935, 4", "content": 34.0}, {"source": "Cohoes American, July 27, 1935, page unknown", "content": 34.0}, {"source": "Troy NY Times Record, July 27, 1935, 7", "content": 34.0}, {"source": "Saratogian, August 22, 1935, 10", "content": 34.0}, {"source": "Troy NY Times Record, August 22, 1935, page unknown", "content": 34.0}, {"source": "Miami Herald, March 24, 1939, C1", "content": 38.0}], "assumed_birth_years": [{"source": "Troy NY Times Record, July 23, 1935, 9", "content": 1901.0}, {"source": "Cohoes American, July 24, 1935, page unknown", "content": 1901.0}, {"source": "Knickerbocker Press, July 24, 1935, page unknown", "content": 1901.0}, {"source": "Albany NY Times-Union, July 27, 1935, 4", "content": 1901.0}, {"source": "Cohoes American, July 27, 1935, page unknown", "content": 1901.0}, {"source": "Troy NY Times Record, July 27, 1935, 7", "content": 1901.0}, {"source": "Saratogian, August 22, 1935, 10", "content": 1901.0}, {"source": "Troy NY Times Record, August 22, 1935, page unknown", "content": 1901.0}, {"source": "Miami Herald, March 24, 1939, C1", "content": 1901.0}], "images": [], "exotic_dancer": [], "fan_dancer": [], "blackface": [], "sepia": [], "connected": {"network": {"nodes": ["(cannot read)", "Adrian Ames", "Adrian Norris", "Al Benson", "Al DeMarco", "Al Garbell", "Al Lucas", "Al Ray", "Alberta Vaughn", "Alden Garrison", "Alfred Carmen", "Alice Rydner", "Alice White", "Allen Carl", "Andy Cliff", "Arica Wild", "Art Bernard", "Art West", "Arthur Budd", "Arthur G. West", "Arthur La Delle", "Babe Allen", "Babe Baker", "Bel Ager", "Benny Pauly", "Bert Sherry", "Bert Wheeler", "Bill Kennedy", "Billie Beryl", "Billie Brannon", "Billie Dale", "Billie Davis", "Billie Dove", "Billie McAllister", "Billie Russell", "Billy \"Senorita\" Herrera", "Billy Brill", "Billy Hayes", "Billy Irwin", "Billy Joy", "Billy Kent", "Billy O'Brien", "Billy Pinnell", "Billy Reed", "Billy Richards", "Billy Rohmer", "Billy Turner", "Billy West", "Blackie Dennis", "Bob Mack", "Bobbie Bell", "Bobbie Davis", "Bobbie Kaye", "Bobbie La Marr", "Bobbie Macklin", "Bobbie Marlowe", "Bobby Allen", "Bobby Anderson", "Bobby Bell", "Bobby Brennan", "Bobby Cummins", "Bobby Dean", "Bobby Dell", "Bobby Ferguson", "Bobby Gay", "Bobby Gordon", "Bobby Hayes", "Bobby Johnson", "Bobby Jones", "Bobby Kork", "Bobby La Rue", "Bobby Lane", "Bobby Leonard", "Bobby McNeer", "Bobby Norman", "Bobby Royce", "Bobby Sullivan", "Bobby Trent", "Bobby Verrill", "Bonnie Lee", "Boots Lavana", "Brooks Twins", "Bud Hart", "Buddy Mayo", "Bunny Dorne", "Buster Brant", "Buster Hewitt", "Carl Clewis", "Carll Morgan", "Carlo Levins", "Carlos J. Henderson", "Carmencita", "Carol Lee", "Carol Mack", "Carroll Davis", "Charles Bell", "Charles Davis", "Chicki Forrest", "Chickie Charms", "Chickie Mears", "Clare St. Clair", "Claudetener", "Cleo Renee", "Connie", "Connie Miller", "Connie Walsh", "Dan Carson", "Danny Brown", "Danny King", "Darryl Gilbert", "Dave Gold", "Dave Shaw", "David J. Doyle", "Davy Lee", "Dawn Sis", "Del Dreer", "Del Le Roy", "Dennis Griffin", "Dickie Ray", "Dion", "Dixie DeLane", "Dixie Dixon", "Dixie Jean", "Dixie Lee", "Dolly Levins", "Dolly O'Day", "Don Holly", "Don Kenyard", "Don Niles", "Don Rand", "Donald Grey", "Doris", "Doris (Dimples) White", "Dorothy Page", "Doyle Mack", "E. Russell", "Earl Partello", "Ed-Na Link", "Eddie Crawford", "Eddie Green", "Eddie La Rue", "Eddie Lee", "Eddie Morton", "Eddie Rogers", "Edmund Link", "Edna Leonard", "Edward Albert Crawford", "Edward Lerner", "El-Kay", "Eli Madlof", "Enesco", "Enna Davison", "Fay Norman", "Ferne Proctor", "Fifi", "Flo Arden", "Florence King", "Frances", "Frances David", "Frances Dee", "Frances Dunn", "Frances Fay", "Frances Hall", "Frances La Verne", "Frances Lee", "Francis Blair", "Francis Bouche", "Francis Loite", "Francis Parker", "Francis Renault", "Francis Russell", "Francis Stillman", "Francis Strom", "Frank Doran", "Frank E. Carroll", "Frank Perry", "Frankie Gondone", "Frankie Huntsinger", "Frankie Stroud", "Fred Munroe", "Fred Noll", "Freddie Barlow", "Freddie Monroe", "Freddie Phillips", "Freddie Renault", "Freddie Wheeler", "Freddy Wheeler", "Fredricka", "Fritz Cantz", "Fritzie Feltz", "Funny Fanny", "G. Doran", "Gabby Lee", "Gale Page", "Garbo", "Garry Teasdale", "Gay Byerd", "Geane Ray", "Gene Baye", "Gene Casali", "Gene Dana", "Gene Darling", "Gene Ford", "Gene Gordon", "Gene Jeanette", "Gene Kauffyn", "Gene Lewis", "Gene Renee", "Gene Russell", "George Denny", "George Hayes", "George Kelly", "George McDowell", "George Oliver", "George Parker", "Georgie Burns", "Georgie Kaye", "Giggles Craig", "Gita Gilmore", "Gorda Davies", "Gus Dreyfus", "Gypsy Dolan", "Half-Pint Jaxon", "Harry Bernie", "Harry E. Brewster", "Harry Fink", "Harry Kelly", "Harvey Lee", "Helen Humes", "Helen Mack", "Helen Tustin", "Herman Ferdinand", "Hot-Cha Hinton", "Howard Parsons", "Ina Gaskill", "Irvin Mazzie", "J. John Howard", "Jabby Caruso", "Jack Craig", "Jack Hughes", "Jack Leystan", "Jack Mason", "Jack Polle", "Jackie Adams", "Jackie Bennett", "Jackie Dayton", "Jackie Giggles", "Jackie Hughes", "Jackie Lane", "Jackie Law", "Jackie Lee", "Jackie Lopez", "Jackie Lorraine", "Jackie Lynch", "Jackie Maye", "Jackie Starr", "Jackie Thomas", "Jacquette La Marr", "James Casalino", "James Costa", "James E. Myers", "Jay Albert", "Jean Arnold", "Jean Barrios", "Jean Darling", "Jean Farrelly", "Jean Jennings", "Jean La Monte", "Jean La Rue", "Jean LaMarr", "Jean Lures", "Jean Malin", "Jean Marlow", "Jean Miller", "Jean Osborne", "Jean Russell", "Jean Taylor", "Jean Val Jean", "Jene Cortez", "Jerry Clayton", "Jerry Faye", "Jerry Francis", "Jerry Girard", "Jerry Nelson", "Jerry Podinsky", "Jerry Trevor", "Jerry Vaughn", "Jessie Lee", "Jessie Rogers", "Jimmie Bernard", "Jimmie Gleen", "Jimmie Sheri", "Jimmy Carrigan", "Jimmy Lyons", "Jo-Jo", "Joan Andrews", "Joan Rogers", "Joann O'Brien", "Joanne Crawford", "Joe Cook", "Joe Hart", "Joe Johnson", "Joe Renard", "Joe Robinson", "John D. May", "John Gravet", "John Koss", "John Lonas", "John Wilton", "Johnnie Langstone", "Johnny Blease", "Johnny David", "Johnny Kaye", "Johnny Mangum", "Jose", "Jose Ayala", "Jose Del Rio", "Joseph Bart", "Jud King", "Julia Stevens", "June Beal", "Kari Daniels", "Karlon Owens", "Karyl Norman", "Kenn King", "Kiki Hall", "Kitty May", "La Carmentita", "Lady Doris", "Lanny Brice", "Larry Turner", "Larry West", "Lee Carroll", "Lee Moore", "Lena Rivers", "Leon Fredericks", "Leon La Verde", "Leonard Jans", "Leonard Soules", "Lester Lamont", "Li Kar", "Linden", "Lloyd Woods", "Lou Lorraine", "Louis Diggs", "Louis Edelstein", "Loyce Trent", "Lucian", "Lyle Mack", "Lyle Page", "Lynn Castle", "Lynn Johnson", "Manuel DeMonte", "Margaret Cook", "Marge Brown", "Marion", "Marjoram", "Marty Deem", "Marvene Nelson", "Mary Brennen", "Marylin Thomas", "Matt Berger", "Max Bellow", "Max Lengel", "Maxine", "Melvin Evans", "Merry Pickford", "Mickey Dell", "Mickey Nelson", "Mickey Standley", "Mildred Martin", "Milton", "Milton LaMaire", "Mitzi", "Mona La Fountaine", "Murray Lenen", "Murray Swanson", "Najean Loy", "Nancy Cauel", "Ned Lynn", "Neil Dornay", "Nicki Gallucci", "Niki Nash", "Niles Marsh", "Nina Mae McKinney", "Nina Montez", "Nora Corona Hancock", "Norman Lewis", "Page Hudeck", "Palafox", "Palofox", "Pat Clayton", "Pat Paree", "Patsy Campbell", "Patsy Keller", "Patty Baker", "Patty Lyons", "Paul", "Paul Coleman", "Paul Gilrey", "Paul La Page", "Paul Russell", "Peaches Browning", "Pep Murray", "Pepper Cortez", "Petite Swanson", "Phil Black", "Phil Craig", "Princess Diane", "Rae Bourbon", "Ralph Gilbert", "Ram'ee", "Ramon Strobeck", "Rani Dorzi", "Ray Foster", "Ray Francis", "Reeder Richards", "Reggie \"Dolly\" Windsor", "Richard Carlson", "Richard Lansin", "Robert A. Lyons", "Robert P. Philip", "Rocky", "Rollie Andrews", "Roni Warren", "Roxy", "Roy Whitemore", "Ruth Roberts", "Sally", "Sam Silvers", "Sandra", "Satch", "Satch Satchell", "Satchell", "Sepia Mae West", "Soni Sinclair", "Sonny Clapp", "Sonny O'Shea", "Stanley E. Caulfield", "Stanley Jabin", "Stanley Rogers", "Steel Smith", "Stuart P. Murphy", "Sunny La Ray", "Tangara", "Tanya Garth", "Ted Cook", "Ted Shaw", "Teddy Cappy", "Teddy Hayes", "Teddy Keller", "Teddy and Yvonne", "Terry La Monte", "Terry Lane", "Terry Phillips", "Terry Stone", "Terry Tremaine", "Tex Hendricks", "The Mystery Dancer", "Thelma Lee", "Theodore Coppi", "Thetis Storey", "Thomas Martin", "Thompson Twin 1", "Thompson Twin 2", "Tiny Kingsmore", "Titanic Kit Russell", "Toby Waddell", "Tom Hose", "Tony Karol", "Toots", "Val Rai", "Val Turek", "Val Varr", "Valda Gray", "Vera Mazzie", "Verne Valdez", "Violet Clements", "Wally Brennan", "Wally Thompson", "Walter Hart", "Walter McDonald", "Walter Munde", "Wesley Davis", "Whitie", "Wilkie Mason", "William Johnson", "William Lee Becker"], "network_id": 1}}, "modularities": {"Louvain": 5, "Clauset-Newman-Moore": 2}, "centralities": {"degree_centrality_100x": 5.653021, "betweenness_centrality_100x": 0.57662, "eigenvector_centrality_100x": 9.816653, "closeness_centrality_100x": 38.019519}, "degrees": {"indegree": 6, "outdegree": 23, "degree": 29}, "node_id": "peppy_carman", "category": "performer", "display": "Peppy Carman", "id": "Peppy Carman"}, {"comments": [], "legal_names": [], "alleged_ages": [], "assumed_birth_years": [], "images": [], "exotic_dancer": [], "fan_dancer": [], "blackface": [], "sepia": [], "connected": {"network": {"nodes": ["(cannot read)", "Adrian Ames", "Adrian Norris", "Al Benson", "Al DeMarco", "Al Garbell", "Al Lucas", "Al Ray", "Alberta Vaughn", "Alden Garrison", "Alfred Carmen", "Alice Rydner", "Alice White", "Allen Carl", "Andy Cliff", "Arica Wild", "Art Bernard", "Art West", "Arthur Budd", "Arthur G. West", "Arthur La Delle", "Babe Allen", "Babe Baker", "Bel Ager", "Benny Pauly", "Bert Sherry", "Bert Wheeler", "Bill Kennedy", "Billie Beryl", "Billie Brannon", "Billie Dale", "Billie Davis", "Billie Dove", "Billie McAllister", "Billie Russell", "Billy \"Senorita\" Herrera", "Billy Brill", "Billy Hayes", "Billy Irwin", "Billy Joy", "Billy Kent", "Billy O'Brien", "Billy Pinnell", "Billy Reed", "Billy Richards", "Billy Rohmer", "Billy Turner", "Billy West", "Blackie Dennis", "Bob Mack", "Bobbie Bell", "Bobbie Davis", "Bobbie Kaye", "Bobbie La Marr", "Bobbie Macklin", "Bobbie Marlowe", "Bobby Allen", "Bobby Anderson", "Bobby Bell", "Bobby Brennan", "Bobby Cummins", "Bobby Dean", "Bobby Dell", "Bobby Ferguson", "Bobby Gay", "Bobby Gordon", "Bobby Hayes", "Bobby Johnson", "Bobby Jones", "Bobby Kork", "Bobby La Rue", "Bobby Lane", "Bobby Leonard", "Bobby McNeer", "Bobby Norman", "Bobby Royce", "Bobby Sullivan", "Bobby Trent", "Bobby Verrill", "Bonnie Lee", "Boots Lavana", "Brooks Twins", "Bud Hart", "Buddy Mayo", "Bunny Dorne", "Buster Brant", "Buster Hewitt", "Carl Clewis", "Carll Morgan", "Carlo Levins", "Carlos J. Henderson", "Carmencita", "Carol Lee", "Carol Mack", "Carroll Davis", "Charles Bell", "Charles Davis", "Chicki Forrest", "Chickie Charms", "Chickie Mears", "Clare St. Clair", "Claudetener", "Cleo Renee", "Connie", "Connie Miller", "Connie Walsh", "Dan Carson", "Danny Brown", "Danny King", "Darryl Gilbert", "Dave Gold", "Dave Shaw", "David J. Doyle", "Davy Lee", "Dawn Sis", "Del Dreer", "Del Le Roy", "Dennis Griffin", "Dickie Ray", "Dion", "Dixie DeLane", "Dixie Dixon", "Dixie Jean", "Dixie Lee", "Dolly Levins", "Dolly O'Day", "Don Holly", "Don Kenyard", "Don Niles", "Don Rand", "Donald Grey", "Doris", "Doris (Dimples) White", "Dorothy Page", "Doyle Mack", "E. Russell", "Earl Partello", "Ed-Na Link", "Eddie Crawford", "Eddie Green", "Eddie La Rue", "Eddie Lee", "Eddie Morton", "Eddie Rogers", "Edmund Link", "Edna Leonard", "Edward Albert Crawford", "Edward Lerner", "El-Kay", "Eli Madlof", "Enesco", "Enna Davison", "Fay Norman", "Ferne Proctor", "Fifi", "Flo Arden", "Florence King", "Frances", "Frances David", "Frances Dee", "Frances Dunn", "Frances Fay", "Frances Hall", "Frances La Verne", "Frances Lee", "Francis Blair", "Francis Bouche", "Francis Loite", "Francis Parker", "Francis Renault", "Francis Russell", "Francis Stillman", "Francis Strom", "Frank Doran", "Frank E. Carroll", "Frank Perry", "Frankie Huntsinger", "Frankie Stroud", "Fred Munroe", "Fred Noll", "Freddie Barlow", "Freddie Monroe", "Freddie Phillips", "Freddie Renault", "Freddie Wheeler", "Freddy Wheeler", "Fredricka", "Fritz Cantz", "Fritzie Feltz", "Funny Fanny", "G. Doran", "Gabby Lee", "Gale Page", "Garbo", "Garry Teasdale", "Gay Byerd", "Geane Ray", "Gene Baye", "Gene Casali", "Gene Dana", "Gene Darling", "Gene Ford", "Gene Gordon", "Gene Jeanette", "Gene Kauffyn", "Gene Lewis", "Gene Renee", "Gene Russell", "George Denny", "George Hayes", "George Kelly", "George McDowell", "George Oliver", "George Parker", "Georgie Burns", "Georgie Kaye", "Giggles Craig", "Gita Gilmore", "Gorda Davies", "Gus Dreyfus", "Gypsy Dolan", "Half-Pint Jaxon", "Harry Bernie", "Harry E. Brewster", "Harry Fink", "Harry Kelly", "Harvey Lee", "Helen Humes", "Helen Mack", "Helen Tustin", "Herman Ferdinand", "Hot-Cha Hinton", "Howard Parsons", "Ina Gaskill", "Irvin Mazzie", "J. John Howard", "Jabby Caruso", "Jack Craig", "Jack Hughes", "Jack Leystan", "Jack Mason", "Jack Polle", "Jackie Adams", "Jackie Bennett", "Jackie Dayton", "Jackie Giggles", "Jackie Hughes", "Jackie Lane", "Jackie Law", "Jackie Lee", "Jackie Lopez", "Jackie Lorraine", "Jackie Lynch", "Jackie Maye", "Jackie Starr", "Jackie Thomas", "Jacquette La Marr", "James Casalino", "James Costa", "James E. Myers", "Jay Albert", "Jean Arnold", "Jean Barrios", "Jean Darling", "Jean Farrelly", "Jean Jennings", "Jean La Monte", "Jean La Rue", "Jean LaMarr", "Jean Lures", "Jean Malin", "Jean Marlow", "Jean Miller", "Jean Osborne", "Jean Russell", "Jean Taylor", "Jean Val Jean", "Jene Cortez", "Jerry Clayton", "Jerry Faye", "Jerry Francis", "Jerry Girard", "Jerry Nelson", "Jerry Podinsky", "Jerry Trevor", "Jerry Vaughn", "Jessie Lee", "Jessie Rogers", "Jimmie Bernard", "Jimmie Gleen", "Jimmie Sheri", "Jimmy Carrigan", "Jimmy Lyons", "Jo-Jo", "Joan Andrews", "Joan Rogers", "Joann O'Brien", "Joanne Crawford", "Joe Cook", "Joe Hart", "Joe Johnson", "Joe Renard", "Joe Robinson", "John D. May", "John Gravet", "John Koss", "John Lonas", "John Wilton", "Johnnie Langstone", "Johnny Blease", "Johnny David", "Johnny Kaye", "Johnny Mangum", "Jose", "Jose Ayala", "Jose Del Rio", "Joseph Bart", "Jud King", "Julia Stevens", "June Beal", "Kari Daniels", "Karlon Owens", "Karyl Norman", "Kenn King", "Kiki Hall", "Kitty May", "La Carmentita", "Lady Doris", "Lanny Brice", "Larry Turner", "Larry West", "Lee Carroll", "Lee Moore", "Lena Rivers", "Leon Fredericks", "Leon La Verde", "Leonard Jans", "Leonard Soules", "Lester Lamont", "Li Kar", "Linden", "Lloyd Woods", "Lou Lorraine", "Louis Diggs", "Louis Edelstein", "Loyce Trent", "Lucian", "Lyle Mack", "Lyle Page", "Lynn Castle", "Lynn Johnson", "Manuel DeMonte", "Margaret Cook", "Marge Brown", "Marion", "Marjoram", "Marty Deem", "Marvene Nelson", "Mary Brennen", "Marylin Thomas", "Matt Berger", "Max Bellow", "Max Lengel", "Maxine", "Melvin Evans", "Merry Pickford", "Mickey Dell", "Mickey Nelson", "Mickey Standley", "Mildred Martin", "Milton", "Milton LaMaire", "Mitzi", "Mona La Fountaine", "Murray Lenen", "Murray Swanson", "Najean Loy", "Nancy Cauel", "Ned Lynn", "Neil Dornay", "Nicki Gallucci", "Niki Nash", "Niles Marsh", "Nina Mae McKinney", "Nina Montez", "Nora Corona Hancock", "Norman Lewis", "Page Hudeck", "Palafox", "Palofox", "Pat Clayton", "Pat Paree", "Patsy Campbell", "Patsy Keller", "Patty Baker", "Patty Lyons", "Paul", "Paul Coleman", "Paul Gilrey", "Paul La Page", "Paul Russell", "Peaches Browning", "Pep Murray", "Pepper Cortez", "Peppy Carman", "Petite Swanson", "Phil Black", "Phil Craig", "Princess Diane", "Rae Bourbon", "Ralph Gilbert", "Ram'ee", "Ramon Strobeck", "Rani Dorzi", "Ray Foster", "Ray Francis", "Reeder Richards", "Reggie \"Dolly\" Windsor", "Richard Carlson", "Richard Lansin", "Robert A. Lyons", "Robert P. Philip", "Rocky", "Rollie Andrews", "Roni Warren", "Roxy", "Roy Whitemore", "Ruth Roberts", "Sally", "Sam Silvers", "Sandra", "Satch", "Satch Satchell", "Satchell", "Sepia Mae West", "Soni Sinclair", "Sonny Clapp", "Sonny O'Shea", "Stanley E. Caulfield", "Stanley Jabin", "Stanley Rogers", "Steel Smith", "Stuart P. Murphy", "Sunny La Ray", "Tangara", "Tanya Garth", "Ted Cook", "Ted Shaw", "Teddy Cappy", "Teddy Hayes", "Teddy Keller", "Teddy and Yvonne", "Terry La Monte", "Terry Lane", "Terry Phillips", "Terry Stone", "Terry Tremaine", "Tex Hendricks", "The Mystery Dancer", "Thelma Lee", "Theodore Coppi", "Thetis Storey", "Thomas Martin", "Thompson Twin 1", "Thompson Twin 2", "Tiny Kingsmore", "Titanic Kit Russell", "Toby Waddell", "Tom Hose", "Tony Karol", "Toots", "Val Rai", "Val Turek", "Val Varr", "Valda Gray", "Vera Mazzie", "Verne Valdez", "Violet Clements", "Wally Brennan", "Wally Thompson", "Walter Hart", "Walter McDonald", "Walter Munde", "Wesley Davis", "Whitie", "Wilkie Mason", "William Johnson", "William Lee Becker"], "network_id": 1}}, "modularities": {"Louvain": 5, "Clauset-Newman-Moore": 7}, "centralities": {"degree_centrality_100x": 0.584795, "betweenness_centrality_100x": 0.0, "eigenvector_centrality_100x": 0.546636, "closeness_centrality_100x": 27.403679}, "degrees": {"indegree": 0, "outdegree": 3, "degree": 3}, "node_id": "frankie_gondone", "category": "performer", "display": "Frankie Gondone", "id": "Frankie Gondone"}, {"comments": [], "legal_names": [], "alleged_ages": [], "assumed_birth_years": [], "images": [], "exotic_dancer": [], "fan_dancer": [], "blackface": [], "sepia": [], "connected": {"network": {"nodes": ["(cannot read)", "Adrian Ames", "Adrian Norris", "Al Benson", "Al DeMarco", "Al Garbell", "Al Lucas", "Al Ray", "Alberta Vaughn", "Alden Garrison", "Alfred Carmen", "Alice Rydner", "Alice White", "Allen Carl", "Andy Cliff", "Arica Wild", "Art Bernard", "Art West", "Arthur Budd", "Arthur G. West", "Arthur La Delle", "Babe Allen", "Babe Baker", "Bel Ager", "Benny Pauly", "Bert Sherry", "Bert Wheeler", "Bill Kennedy", "Billie Beryl", "Billie Brannon", "Billie Dale", "Billie Davis", "Billie Dove", "Billie McAllister", "Billie Russell", "Billy \"Senorita\" Herrera", "Billy Brill", "Billy Hayes", "Billy Irwin", "Billy Joy", "Billy Kent", "Billy O'Brien", "Billy Pinnell", "Billy Reed", "Billy Richards", "Billy Rohmer", "Billy Turner", "Billy West", "Blackie Dennis", "Bob Mack", "Bobbie Bell", "Bobbie Davis", "Bobbie Kaye", "Bobbie La Marr", "Bobbie Macklin", "Bobbie Marlowe", "Bobby Allen", "Bobby Anderson", "Bobby Bell", "Bobby Brennan", "Bobby Cummins", "Bobby Dean", "Bobby Dell", "Bobby Ferguson", "Bobby Gay", "Bobby Gordon", "Bobby Hayes", "Bobby Johnson", "Bobby Jones", "Bobby Kork", "Bobby La Rue", "Bobby Lane", "Bobby Leonard", "Bobby McNeer", "Bobby Norman", "Bobby Royce", "Bobby Sullivan", "Bobby Trent", "Bobby Verrill", "Bonnie Lee", "Boots Lavana", "Brooks Twins", "Bud Hart", "Buddy Mayo", "Bunny Dorne", "Buster Brant", "Buster Hewitt", "Carl Clewis", "Carll Morgan", "Carlo Levins", "Carlos J. Henderson", "Carmencita", "Carol Lee", "Carol Mack", "Carroll Davis", "Charles Bell", "Charles Davis", "Chicki Forrest", "Chickie Charms", "Chickie Mears", "Clare St. Clair", "Claudetener", "Cleo Renee", "Connie", "Connie Miller", "Connie Walsh", "Dan Carson", "Danny Brown", "Danny King", "Darryl Gilbert", "Dave Gold", "Dave Shaw", "David J. Doyle", "Davy Lee", "Dawn Sis", "Del Dreer", "Del Le Roy", "Dennis Griffin", "Dickie Ray", "Dion", "Dixie DeLane", "Dixie Dixon", "Dixie Jean", "Dixie Lee", "Dolly Levins", "Dolly O'Day", "Don Holly", "Don Kenyard", "Don Niles", "Don Rand", "Donald Grey", "Doris", "Doris (Dimples) White", "Dorothy Page", "Doyle Mack", "E. Russell", "Earl Partello", "Ed-Na Link", "Eddie Crawford", "Eddie Green", "Eddie La Rue", "Eddie Lee", "Eddie Morton", "Eddie Rogers", "Edmund Link", "Edna Leonard", "Edward Albert Crawford", "Edward Lerner", "El-Kay", "Eli Madlof", "Enesco", "Enna Davison", "Fay Norman", "Ferne Proctor", "Fifi", "Flo Arden", "Florence King", "Frances", "Frances David", "Frances Dee", "Frances Dunn", "Frances Fay", "Frances Hall", "Frances La Verne", "Frances Lee", "Francis Blair", "Francis Bouche", "Francis Loite", "Francis Parker", "Francis Renault", "Francis Russell", "Francis Stillman", "Francis Strom", "Frank Doran", "Frank E. Carroll", "Frank Perry", "Frankie Gondone", "Frankie Huntsinger", "Frankie Stroud", "Fred Munroe", "Fred Noll", "Freddie Barlow", "Freddie Monroe", "Freddie Phillips", "Freddie Renault", "Freddie Wheeler", "Freddy Wheeler", "Fredricka", "Fritz Cantz", "Fritzie Feltz", "Funny Fanny", "G. Doran", "Gabby Lee", "Gale Page", "Garbo", "Garry Teasdale", "Gay Byerd", "Geane Ray", "Gene Baye", "Gene Casali", "Gene Dana", "Gene Darling", "Gene Ford", "Gene Gordon", "Gene Jeanette", "Gene Kauffyn", "Gene Lewis", "Gene Renee", "Gene Russell", "George Denny", "George Hayes", "George Kelly", "George McDowell", "George Oliver", "George Parker", "Georgie Burns", "Georgie Kaye", "Giggles Craig", "Gita Gilmore", "Gorda Davies", "Gus Dreyfus", "Gypsy Dolan", "Half-Pint Jaxon", "Harry Bernie", "Harry E. Brewster", "Harry Fink", "Harry Kelly", "Harvey Lee", "Helen Humes", "Helen Mack", "Helen Tustin", "Herman Ferdinand", "Hot-Cha Hinton", "Howard Parsons", "Ina Gaskill", "Irvin Mazzie", "J. John Howard", "Jabby Caruso", "Jack Craig", "Jack Hughes", "Jack Leystan", "Jack Mason", "Jack Polle", "Jackie Adams", "Jackie Bennett", "Jackie Dayton", "Jackie Giggles", "Jackie Hughes", "Jackie Lane", "Jackie Law", "Jackie Lee", "Jackie Lopez", "Jackie Lorraine", "Jackie Lynch", "Jackie Maye", "Jackie Starr", "Jackie Thomas", "Jacquette La Marr", "James Casalino", "James Costa", "James E. Myers", "Jay Albert", "Jean Arnold", "Jean Barrios", "Jean Darling", "Jean Farrelly", "Jean Jennings", "Jean La Monte", "Jean La Rue", "Jean LaMarr", "Jean Lures", "Jean Malin", "Jean Marlow", "Jean Miller", "Jean Osborne", "Jean Russell", "Jean Taylor", "Jean Val Jean", "Jene Cortez", "Jerry Clayton", "Jerry Faye", "Jerry Francis", "Jerry Girard", "Jerry Nelson", "Jerry Podinsky", "Jerry Trevor", "Jerry Vaughn", "Jessie Lee", "Jessie Rogers", "Jimmie Bernard", "Jimmie Gleen", "Jimmie Sheri", "Jimmy Carrigan", "Jimmy Lyons", "Jo-Jo", "Joan Andrews", "Joan Rogers", "Joann O'Brien", "Joanne Crawford", "Joe Cook", "Joe Hart", "Joe Johnson", "Joe Renard", "Joe Robinson", "John D. May", "John Gravet", "John Koss", "John Lonas", "John Wilton", "Johnnie Langstone", "Johnny Blease", "Johnny David", "Johnny Kaye", "Johnny Mangum", "Jose", "Jose Ayala", "Jose Del Rio", "Joseph Bart", "Jud King", "Julia Stevens", "June Beal", "Kari Daniels", "Karlon Owens", "Karyl Norman", "Kenn King", "Kiki Hall", "Kitty May", "La Carmentita", "Lady Doris", "Lanny Brice", "Larry Turner", "Larry West", "Lee Carroll", "Lee Moore", "Lena Rivers", "Leon Fredericks", "Leon La Verde", "Leonard Jans", "Leonard Soules", "Lester Lamont", "Li Kar", "Linden", "Lloyd Woods", "Lou Lorraine", "Louis Diggs", "Louis Edelstein", "Loyce Trent", "Lucian", "Lyle Mack", "Lyle Page", "Lynn Castle", "Lynn Johnson", "Manuel DeMonte", "Margaret Cook", "Marge Brown", "Marion", "Marjoram", "Marty Deem", "Marvene Nelson", "Mary Brennen", "Marylin Thomas", "Matt Berger", "Max Bellow", "Max Lengel", "Maxine", "Melvin Evans", "Merry Pickford", "Mickey Dell", "Mickey Nelson", "Mickey Standley", "Mildred Martin", "Milton", "Milton LaMaire", "Mitzi", "Mona La Fountaine", "Murray Lenen", "Murray Swanson", "Najean Loy", "Nancy Cauel", "Ned Lynn", "Neil Dornay", "Nicki Gallucci", "Niki Nash", "Niles Marsh", "Nina Mae McKinney", "Nina Montez", "Nora Corona Hancock", "Norman Lewis", "Page Hudeck", "Palafox", "Palofox", "Pat Clayton", "Pat Paree", "Patsy Campbell", "Patsy Keller", "Patty Baker", "Patty Lyons", "Paul", "Paul Coleman", "Paul Gilrey", "Paul La Page", "Paul Russell", "Peaches Browning", "Pep Murray", "Pepper Cortez", "Peppy Carman", "Petite Swanson", "Phil Black", "Phil Craig", "Princess Diane", "Rae Bourbon", "Ralph Gilbert", "Ram'ee", "Ramon Strobeck", "Rani Dorzi", "Ray Foster", "Ray Francis", "Reeder Richards", "Reggie \"Dolly\" Windsor", "Richard Carlson", "Richard Lansin", "Robert A. Lyons", "Robert P. Philip", "Rocky", "Rollie Andrews", "Roni Warren", "Roxy", "Roy Whitemore", "Ruth Roberts", "Sally", "Sam Silvers", "Sandra", "Satch", "Satch Satchell", "Satchell", "Sepia Mae West", "Soni Sinclair", "Sonny Clapp", "Sonny O'Shea", "Stanley E. Caulfield", "Stanley Jabin", "Stanley Rogers", "Steel Smith", "Stuart P. Murphy", "Sunny La Ray", "Tangara", "Tanya Garth", "Ted Cook", "Ted Shaw", "Teddy Cappy", "Teddy Hayes", "Teddy and Yvonne", "Terry La Monte", "Terry Lane", "Terry Phillips", "Terry Stone", "Terry Tremaine", "Tex Hendricks", "The Mystery Dancer", "Thelma Lee", "Theodore Coppi", "Thetis Storey", "Thomas Martin", "Thompson Twin 1", "Thompson Twin 2", "Tiny Kingsmore", "Titanic Kit Russell", "Toby Waddell", "Tom Hose", "Tony Karol", "Toots", "Val Rai", "Val Turek", "Val Varr", "Valda Gray", "Vera Mazzie", "Verne Valdez", "Violet Clements", "Wally Brennan", "Wally Thompson", "Walter Hart", "Walter McDonald", "Walter Munde", "Wesley Davis", "Whitie", "Wilkie Mason", "William Johnson", "William Lee Becker"], "network_id": 1}}, "modularities": {"Louvain": 5, "Clauset-Newman-Moore": 2}, "centralities": {"degree_centrality_100x": 3.508772, "betweenness_centrality_100x": 0.135357, "eigenvector_centrality_100x": 6.120728, "closeness_centrality_100x": 34.183971}, "degrees": {"indegree": 1, "outdegree": 17, "degree": 18}, "node_id": "teddy_keller", "category": "performer", "display": "Teddy Keller", "id": "Teddy Keller"}, {"comments": [{"source": "Hackensack NJ Record, September 13, 1934, 2 (488668361)", "content": "From Club Richman"}, {"source": "Rochester Times-Union, June 20, 1935, 8", "content": "\"Lucian, who refuses to disclose his real name, today said he and his 'boys' were waiting final word from Michaels as to whether it would be possible to continue their show at the nightclub. Michaels, however, has apparently abandoned his fight against Sheriff Malley, who ordered the show closed. The Chateau maestro has not talked with Lucian since Tuesday. Asked if he had settled terms of his contract with Michaels, which is said to run to July 1, Lucian replied: 'He'll take care of that, all right, he is a fine man.' 'I'm not interested in the contract at all,' he said, 'I'm more concerned at leaving town with a clean record. If I don't hear from Michaels today, I'm going to take my boys to New York tomorrow, where we have an engagement.' Sheriff Malley, who ordered the show to stop after last Saturday's performance, today said the case was closed as far as he was concerned. Public Safety Commissioner Walter P. Cox today again stated he had received no complaints about the playboys who are staying at a downtown hotel. He said he was 'not looking for trouble' and that no steps would be taken unless complaints are received about the troupe.\""}, {"source": "Miami Herald, January 2, 1939, 6", "content": "\"The Voice In a Million\""}, {"source": "Tucson Daily Citizen, February 1, 1952, page unknown", "content": "\"The Male Sophie Tucker\"; \"Last of the Red Hot Papas\""}, {"source": "San Mateo CA Times, April 26, 1968, page unknown", "content": "\"wry quips with ringsiders\"; \"male Sophie Tucker\"; "}], "legal_names": [{"source": "Hackensack NJ Record, September 13, 1934, 2 (488668361)", "content": "Charles Phelps"}, {"source": "Letter from Harvey Lee to Pete Petillo, UALR archives; Letter from Harvey Lee to Richie Grassano and Johnny Magliocco, UALR archives; Letter from Harvey Lee to Joe Daniels, UALR archives, March 12, 1948", "content": "Lucian Phelps"}, {"source": "San Mateo CA Times, April 26, 1968, page unknown", "content": "Lucian Phelps"}], "alleged_ages": [{"source": "Hackensack NJ Record, September 13, 1934, 2 (488668361)", "content": 28.0}], "assumed_birth_years": [{"source": "Hackensack NJ Record, September 13, 1934, 2 (488668361)", "content": 1906.0}], "images": [], "exotic_dancer": [], "fan_dancer": [], "blackface": [], "sepia": [], "connected": {"network": {"nodes": ["(cannot read)", "Adrian Ames", "Adrian Norris", "Al Benson", "Al DeMarco", "Al Garbell", "Al Lucas", "Al Ray", "Alberta Vaughn", "Alden Garrison", "Alfred Carmen", "Alice Rydner", "Alice White", "Allen Carl", "Andy Cliff", "Arica Wild", "Art Bernard", "Art West", "Arthur Budd", "Arthur G. West", "Arthur La Delle", "Babe Allen", "Babe Baker", "Bel Ager", "Benny Pauly", "Bert Sherry", "Bert Wheeler", "Bill Kennedy", "Billie Beryl", "Billie Brannon", "Billie Dale", "Billie Davis", "Billie Dove", "Billie McAllister", "Billie Russell", "Billy \"Senorita\" Herrera", "Billy Brill", "Billy Hayes", "Billy Irwin", "Billy Joy", "Billy Kent", "Billy O'Brien", "Billy Pinnell", "Billy Reed", "Billy Richards", "Billy Rohmer", "Billy Turner", "Billy West", "Blackie Dennis", "Bob Mack", "Bobbie Bell", "Bobbie Davis", "Bobbie Kaye", "Bobbie La Marr", "Bobbie Macklin", "Bobbie Marlowe", "Bobby Allen", "Bobby Anderson", "Bobby Bell", "Bobby Brennan", "Bobby Cummins", "Bobby Dean", "Bobby Dell", "Bobby Ferguson", "Bobby Gay", "Bobby Gordon", "Bobby Hayes", "Bobby Johnson", "Bobby Jones", "Bobby Kork", "Bobby La Rue", "Bobby Lane", "Bobby Leonard", "Bobby McNeer", "Bobby Norman", "Bobby Royce", "Bobby Sullivan", "Bobby Trent", "Bobby Verrill", "Bonnie Lee", "Boots Lavana", "Brooks Twins", "Bud Hart", "Buddy Mayo", "Bunny Dorne", "Buster Brant", "Buster Hewitt", "Carl Clewis", "Carll Morgan", "Carlo Levins", "Carlos J. Henderson", "Carmencita", "Carol Lee", "Carol Mack", "Carroll Davis", "Charles Bell", "Charles Davis", "Chicki Forrest", "Chickie Charms", "Chickie Mears", "Clare St. Clair", "Claudetener", "Cleo Renee", "Connie", "Connie Miller", "Connie Walsh", "Dan Carson", "Danny Brown", "Danny King", "Darryl Gilbert", "Dave Gold", "Dave Shaw", "David J. Doyle", "Davy Lee", "Dawn Sis", "Del Dreer", "Del Le Roy", "Dennis Griffin", "Dickie Ray", "Dion", "Dixie DeLane", "Dixie Dixon", "Dixie Jean", "Dixie Lee", "Dolly Levins", "Dolly O'Day", "Don Holly", "Don Kenyard", "Don Niles", "Don Rand", "Donald Grey", "Doris", "Doris (Dimples) White", "Dorothy Page", "Doyle Mack", "E. Russell", "Earl Partello", "Ed-Na Link", "Eddie Crawford", "Eddie Green", "Eddie La Rue", "Eddie Lee", "Eddie Morton", "Eddie Rogers", "Edmund Link", "Edna Leonard", "Edward Albert Crawford", "Edward Lerner", "El-Kay", "Eli Madlof", "Enesco", "Enna Davison", "Fay Norman", "Ferne Proctor", "Fifi", "Flo Arden", "Florence King", "Frances", "Frances David", "Frances Dee", "Frances Dunn", "Frances Fay", "Frances Hall", "Frances La Verne", "Frances Lee", "Francis Blair", "Francis Bouche", "Francis Loite", "Francis Parker", "Francis Renault", "Francis Russell", "Francis Stillman", "Francis Strom", "Frank Doran", "Frank E. Carroll", "Frank Perry", "Frankie Gondone", "Frankie Huntsinger", "Frankie Stroud", "Fred Munroe", "Fred Noll", "Freddie Barlow", "Freddie Monroe", "Freddie Phillips", "Freddie Renault", "Freddie Wheeler", "Freddy Wheeler", "Fredricka", "Fritz Cantz", "Fritzie Feltz", "Funny Fanny", "G. Doran", "Gabby Lee", "Gale Page", "Garbo", "Garry Teasdale", "Gay Byerd", "Geane Ray", "Gene Baye", "Gene Casali", "Gene Dana", "Gene Darling", "Gene Ford", "Gene Gordon", "Gene Jeanette", "Gene Kauffyn", "Gene Lewis", "Gene Renee", "Gene Russell", "George Denny", "George Hayes", "George Kelly", "George McDowell", "George Oliver", "George Parker", "Georgie Burns", "Georgie Kaye", "Giggles Craig", "Gita Gilmore", "Gorda Davies", "Gus Dreyfus", "Gypsy Dolan", "Half-Pint Jaxon", "Harry Bernie", "Harry E. Brewster", "Harry Fink", "Harry Kelly", "Harvey Lee", "Helen Humes", "Helen Mack", "Helen Tustin", "Herman Ferdinand", "Hot-Cha Hinton", "Howard Parsons", "Ina Gaskill", "Irvin Mazzie", "J. John Howard", "Jabby Caruso", "Jack Craig", "Jack Hughes", "Jack Leystan", "Jack Mason", "Jack Polle", "Jackie Adams", "Jackie Bennett", "Jackie Dayton", "Jackie Giggles", "Jackie Hughes", "Jackie Lane", "Jackie Law", "Jackie Lee", "Jackie Lopez", "Jackie Lorraine", "Jackie Lynch", "Jackie Maye", "Jackie Starr", "Jackie Thomas", "Jacquette La Marr", "James Casalino", "James Costa", "James E. Myers", "Jay Albert", "Jean Arnold", "Jean Barrios", "Jean Darling", "Jean Farrelly", "Jean Jennings", "Jean La Monte", "Jean La Rue", "Jean LaMarr", "Jean Lures", "Jean Malin", "Jean Marlow", "Jean Miller", "Jean Osborne", "Jean Russell", "Jean Taylor", "Jean Val Jean", "Jene Cortez", "Jerry Clayton", "Jerry Faye", "Jerry Francis", "Jerry Girard", "Jerry Nelson", "Jerry Podinsky", "Jerry Trevor", "Jerry Vaughn", "Jessie Lee", "Jessie Rogers", "Jimmie Bernard", "Jimmie Gleen", "Jimmie Sheri", "Jimmy Carrigan", "Jimmy Lyons", "Jo-Jo", "Joan Andrews", "Joan Rogers", "Joann O'Brien", "Joanne Crawford", "Joe Cook", "Joe Hart", "Joe Johnson", "Joe Renard", "Joe Robinson", "John D. May", "John Gravet", "John Koss", "John Lonas", "John Wilton", "Johnnie Langstone", "Johnny Blease", "Johnny David", "Johnny Kaye", "Johnny Mangum", "Jose", "Jose Ayala", "Jose Del Rio", "Joseph Bart", "Jud King", "Julia Stevens", "June Beal", "Kari Daniels", "Karlon Owens", "Karyl Norman", "Kenn King", "Kiki Hall", "Kitty May", "La Carmentita", "Lady Doris", "Lanny Brice", "Larry Turner", "Larry West", "Lee Carroll", "Lee Moore", "Lena Rivers", "Leon Fredericks", "Leon La Verde", "Leonard Jans", "Leonard Soules", "Lester Lamont", "Li Kar", "Linden", "Lloyd Woods", "Lou Lorraine", "Louis Diggs", "Louis Edelstein", "Loyce Trent", "Lyle Mack", "Lyle Page", "Lynn Castle", "Lynn Johnson", "Manuel DeMonte", "Margaret Cook", "Marge Brown", "Marion", "Marjoram", "Marty Deem", "Marvene Nelson", "Mary Brennen", "Marylin Thomas", "Matt Berger", "Max Bellow", "Max Lengel", "Maxine", "Melvin Evans", "Merry Pickford", "Mickey Dell", "Mickey Nelson", "Mickey Standley", "Mildred Martin", "Milton", "Milton LaMaire", "Mitzi", "Mona La Fountaine", "Murray Lenen", "Murray Swanson", "Najean Loy", "Nancy Cauel", "Ned Lynn", "Neil Dornay", "Nicki Gallucci", "Niki Nash", "Niles Marsh", "Nina Mae McKinney", "Nina Montez", "Nora Corona Hancock", "Norman Lewis", "Page Hudeck", "Palafox", "Palofox", "Pat Clayton", "Pat Paree", "Patsy Campbell", "Patsy Keller", "Patty Baker", "Patty Lyons", "Paul", "Paul Coleman", "Paul Gilrey", "Paul La Page", "Paul Russell", "Peaches Browning", "Pep Murray", "Pepper Cortez", "Peppy Carman", "Petite Swanson", "Phil Black", "Phil Craig", "Princess Diane", "Rae Bourbon", "Ralph Gilbert", "Ram'ee", "Ramon Strobeck", "Rani Dorzi", "Ray Foster", "Ray Francis", "Reeder Richards", "Reggie \"Dolly\" Windsor", "Richard Carlson", "Richard Lansin", "Robert A. Lyons", "Robert P. Philip", "Rocky", "Rollie Andrews", "Roni Warren", "Roxy", "Roy Whitemore", "Ruth Roberts", "Sally", "Sam Silvers", "Sandra", "Satch", "Satch Satchell", "Satchell", "Sepia Mae West", "Soni Sinclair", "Sonny Clapp", "Sonny O'Shea", "Stanley E. Caulfield", "Stanley Jabin", "Stanley Rogers", "Steel Smith", "Stuart P. Murphy", "Sunny La Ray", "Tangara", "Tanya Garth", "Ted Cook", "Ted Shaw", "Teddy Cappy", "Teddy Hayes", "Teddy Keller", "Teddy and Yvonne", "Terry La Monte", "Terry Lane", "Terry Phillips", "Terry Stone", "Terry Tremaine", "Tex Hendricks", "The Mystery Dancer", "Thelma Lee", "Theodore Coppi", "Thetis Storey", "Thomas Martin", "Thompson Twin 1", "Thompson Twin 2", "Tiny Kingsmore", "Titanic Kit Russell", "Toby Waddell", "Tom Hose", "Tony Karol", "Toots", "Val Rai", "Val Turek", "Val Varr", "Valda Gray", "Vera Mazzie", "Verne Valdez", "Violet Clements", "Wally Brennan", "Wally Thompson", "Walter Hart", "Walter McDonald", "Walter Munde", "Wesley Davis", "Whitie", "Wilkie Mason", "William Johnson", "William Lee Becker"], "network_id": 1}}, "modularities": {"Louvain": 5, "Clauset-Newman-Moore": 7}, "centralities": {"degree_centrality_100x": 1.754386, "betweenness_centrality_100x": 0.100139, "eigenvector_centrality_100x": 0.938464, "closeness_centrality_100x": 29.03179}, "degrees": {"indegree": 6, "outdegree": 3, "degree": 9}, "node_id": "lucian", "category": "performer", "display": "Lucian", "id": "Lucian"}], "links": [{"coLocated": {"Echo Tavern (Albany, NY)": [["1935-08-14", "1935-08-22", "1935-09-03", "1935-09-04", "1935-09-13", "1935-09-18", "1935-09-27", "1935-10-09"]], "Topper Cafe (Philadelphia, PA)": [["1940-11-30", "1940-12-06", "1940-12-07", "1940-12-13", "1940-12-14", "1940-12-21", "1940-12-30"]]}, "revues": ["Jack Mason's Play Boy Revue", "Peppy Carman and His All-Boy Revue"], "cities": ["Albany, NY", "Philadelphia, PA"], "weights": {"dateGroups": 1, "venues": 2}, "edge_id": "peppy_carman_teddy_keller", "comments": {"venues": {}, "cities": {}, "revues": {}}, "general_comments": [], "found": ["1935-08-14", "1935-08-22", "1935-09-03", "1935-09-04", "1935-09-13", "1935-09-18", "1935-09-27", "1935-10-09", "1940-11-30", "1940-12-06", "1940-12-07", "1940-12-13", "1940-12-14", "1940-12-21", "1940-12-30"], "source": "Peppy Carman", "target": "Teddy Keller"}, {"coLocated": {"Topper Cafe (Philadelphia, PA)": [["1940-11-30", "1940-12-06", "1940-12-07", "1940-12-13", "1940-12-14", "1940-12-21", "1940-12-30"]]}, "revues": ["Peppy Carman and His All-Boy Revue"], "cities": ["Philadelphia, PA"], "weights": {"dateGroups": 1, "venues": 1}, "edge_id": "peppy_carman_frankie_gondone", "comments": {"venues": {}, "cities": {}, "revues": {}}, "general_comments": [], "found": ["1940-11-30", "1940-12-06", "1940-12-07", "1940-12-13", "1940-12-14", "1940-12-21", "1940-12-30"], "source": "Peppy Carman", "target": "Frankie Gondone"}, {"coLocated": {"Topper Cafe (Philadelphia, PA)": [["1940-11-30", "1940-12-06", "1940-12-07", "1940-12-13", "1940-12-14", "1940-12-21", "1940-12-30"]]}, "revues": ["Peppy Carman and His All-Boy Revue"], "cities": ["Philadelphia, PA"], "weights": {"dateGroups": 1, "venues": 1}, "edge_id": "lucian_peppy_carman", "comments": {"venues": {}, "cities": {}, "revues": {}}, "general_comments": [], "found": ["1940-11-30", "1940-12-06", "1940-12-07", "1940-12-13", "1940-12-14", "1940-12-21", "1940-12-30"], "source": "Peppy Carman", "target": "Lucian"}, {"coLocated": {"Topper Cafe (Philadelphia, PA)": [["1940-11-30", "1940-12-06", "1940-12-07", "1940-12-13", "1940-12-14", "1940-12-21", "1940-12-30"]]}, "revues": ["Peppy Carman and His All-Boy Revue"], "cities": ["Philadelphia, PA"], "weights": {"dateGroups": 1, "venues": 1}, "edge_id": "lucian_frankie_gondone", "comments": {"venues": {}, "cities": {}, "revues": {}}, "general_comments": [], "found": ["1940-11-30", "1940-12-06", "1940-12-07", "1940-12-13", "1940-12-14", "1940-12-21", "1940-12-30"], "source": "Frankie Gondone", "target": "Lucian"}, {"coLocated": {"Topper Cafe (Philadelphia, PA)": [["1940-11-30", "1940-12-06", "1940-12-07", "1940-12-13", "1940-12-14", "1940-12-21", "1940-12-30"]]}, "revues": ["Peppy Carman and His All-Boy Revue"], "cities": ["Philadelphia, PA"], "weights": {"dateGroups": 1, "venues": 1}, "edge_id": "teddy_keller_frankie_gondone", "comments": {"venues": {}, "cities": {}, "revues": {}}, "general_comments": [], "found": ["1940-11-30", "1940-12-06", "1940-12-07", "1940-12-13", "1940-12-14", "1940-12-21", "1940-12-30"], "source": "Frankie Gondone", "target": "Teddy Keller"}, {"coLocated": {"Topper Cafe (Philadelphia, PA)": [["1940-11-30", "1940-12-06", "1940-12-07", "1940-12-13", "1940-12-14", "1940-12-21", "1940-12-30"]]}, "revues": ["Peppy Carman and His All-Boy Revue"], "cities": ["Philadelphia, PA"], "weights": {"dateGroups": 1, "venues": 1}, "edge_id": "lucian_teddy_keller", "comments": {"venues": {}, "cities": {}, "revues": {}}, "general_comments": [], "found": ["1940-11-30", "1940-12-06", "1940-12-07", "1940-12-13", "1940-12-14", "1940-12-21", "1940-12-30"], "source": "Teddy Keller", "target": "Lucian"}], "createdDate": "2021-09-01 14:41:57"}