{"not_found": ["Baltimore Afro-American", "Jamestown Evening Journal", "Camden NJ Courier-Post", "**Unlisted QMH source 2", "Albany Times-Union", "Albany Times-Union, date unknown", "Amsterdam Evening Recorder", "Baldwinsville Gazette and Farmers Journal", "Billboard"], "firstpage_urls": {"Camden NJ Courier-Post": {"1943-July-19": "https://www.newspapers.com/paper/courier-post/3767/"}, "Camden Courier-Post": {"1943-July-19": "https://www.newspapers.com/image/480816020/", "1938-August-4": "https://www.newspapers.com/image/480354240/", "1940-December-13": "https://www.newspapers.com/image/480445295/", "1933-November-20": "https://www.newspapers.com/image/479165134/", "1930-October-25": "https://www.newspapers.com/image/479480604/"}, "Minneapolis Star Tribune": {"1949-August-12": "https://www.newspapers.com/image/180751294/"}, "Hazleton Plain Speaker": {"1935-November-23": "https://www.newspapers.com/image/502428434/"}, "Indianapolis Star": {"1930-April-9": "https://www.newspapers.com/image/104982910/"}, "Brooklyn Daily Eagle": {"1926-January-19": "https://www.newspapers.com/image/57560158/", "1931-April-20": "https://www.newspapers.com/image/57365970/", "1935-August-12": "https://www.newspapers.com/image/52692560/", "1939-December-1": "https://www.newspapers.com/image/52769231/", "1924-December-10": "https://www.newspapers.com/image/59858173/", "1939-December-15": "https://www.newspapers.com/image/52775947/", "1939-December-22": "https://www.newspapers.com/image/52778233/", "1939-December-29": "https://www.newspapers.com/image/52780071/", "1934-December-9": "https://www.newspapers.com/image/59982971/", "1932-February-12": "https://www.newspapers.com/image/59867387/", "1926-February-16": "https://www.newspapers.com/image/57556261/", "1930-February-18": "https://www.newspapers.com/image/59907908/", "1931-February-23": "https://www.newspapers.com/image/57577241/", "1933-February-6": "https://www.newspapers.com/image/59864495/", "1934-January-17": "https://www.newspapers.com/image/59990979/", "1934-January-29": "https://www.newspapers.com/image/59998785/", "1944-July-12": "https://www.newspapers.com/image/54498728/", "1944-July-2": "https://www.newspapers.com/image/54497868/", "1935-July-22": "https://www.newspapers.com/image/52620380/", "1933-June-16": "https://www.newspapers.com/image/59988082/", "1934-June-19": "https://www.newspapers.com/image/59990818/", "1925-June-25": "https://www.newspapers.com/image/59906960/", "1926-March-2": "https://www.newspapers.com/image/59844078/", "1931-March-21": "https://www.newspapers.com/image/59841526/", "1932-March-24": "https://www.newspapers.com/image/57401429/", "1926-March-30": "https://www.newspapers.com/image/59850924/", "1911-March-5": "https://www.newspapers.com/image/53888337/", "1932-May-18": "https://www.newspapers.com/image/59971651/", "1934-May-19": "https://www.newspapers.com/image/58260820/", "1936-May-20": "https://www.newspapers.com/image/52653987/", "1934-November-1": "https://www.newspapers.com/image/59970943/", "1939-November-10": "https://www.newspapers.com/image/52759027/", "1938-November-11": "https://www.newspapers.com/image/52621607/", "1934-November-24": "https://www.newspapers.com/image/59992165/", "1939-November-24": "https://www.newspapers.com/image/52767530/", "1930-November-26": "https://www.newspapers.com/image/58229139/", "1934-November-26": "https://www.newspapers.com/image/59994024/", "1934-November-27": "https://www.newspapers.com/image/59994611/", "1930-November-29": "https://www.newspapers.com/image/58229213/", "1938-November-4": "https://www.newspapers.com/image/52617687/", "1931-November-8": "https://www.newspapers.com/image/57388105/", "1928-October-2": "https://www.newspapers.com/image/57552443/", "1941-October-24": "https://www.newspapers.com/image/52805525/", "1941-October-3": "https://www.newspapers.com/image/52804929/", "1930-December-1": "https://www.newspapers.com/image/58061423/", "1930-February-19": "https://www.newspapers.com/image/59908407/"}, "Aiken Standard": {"1934-January-24": "https://www.newspapers.com/image/14191579/"}, "Akron Beacon Journal": {"1937-April-13": "https://www.newspapers.com/image/228680532/", "1930-August-1": "https://www.newspapers.com/image/228836010/", "1937-August-31": "https://www.newspapers.com/image/228732461/", "1935-December-11": "https://www.newspapers.com/image/228473284/", "1935-December-12": "https://www.newspapers.com/image/228473875/", "1935-December-14": "https://www.newspapers.com/image/228475501/", "1935-December-16": "https://www.newspapers.com/image/228475850/", "1935-December-18": "https://www.newspapers.com/image/228476702/", "1935-December-19": "https://www.newspapers.com/image/228477114/", "1935-December-4": "https://www.newspapers.com/image/228469544/", "1935-December-6": "https://www.newspapers.com/image/228470851/", "1935-December-9": "https://www.newspapers.com/image/228472133/", "1936-February-26": "https://www.newspapers.com/image/228592586/", "1930-July-24": "https://www.newspapers.com/image/228838456/", "1930-July-25": "https://www.newspapers.com/image/228839041/", "1930-July-26": "https://www.newspapers.com/image/228839791/", "1930-July-28": "https://www.newspapers.com/image/228840270/", "1930-July-29": "https://www.newspapers.com/image/228840841/", "1930-July-30": "https://www.newspapers.com/image/228841609/", "1930-July-31": "https://www.newspapers.com/image/228842301/", "1950-June-16": "https://www.newspapers.com/image/146521837/", "1941-June-20": "https://www.newspapers.com/image/148379598/", "1941-June-24": "https://www.newspapers.com/image/148381058/", "1941-June-26": "https://www.newspapers.com/image/148381610/", "1941-June-27": "https://www.newspapers.com/image/148381954/", "1936-November-27": "https://www.newspapers.com/image/228723256/", "1937-October-25": "https://www.newspapers.com/image/228714205/", "1937-October-27": "https://www.newspapers.com/image/228714522/", "1937-October-30": "https://www.newspapers.com/image/228715079/", "1937-September-1": "https://www.newspapers.com/image/228655021/", "1936-September-23": "https://www.newspapers.com/image/228734897/", "1935-December-20": "https://www.newspapers.com/image/228477561/", "1935-December-21": "https://www.newspapers.com/image/228478175/", "1935-December-5": "https://www.newspapers.com/image/228470131/", "1935-December-7": "https://www.newspapers.com/image/228471739/"}, "Albuquerque Journal": {"1932-April-23": "https://www.newspapers.com/image/156635999/", "1935-August-29": "https://www.newspapers.com/image/156593370/", "1932-September-10": "https://www.newspapers.com/image/156255926/", "1932-September-11": "https://www.newspapers.com/image/156256266/", "1932-September-14": "https://www.newspapers.com/image/156257341/", "1932-September-4": "https://www.newspapers.com/image/156253780/", "1932-September-7": "https://www.newspapers.com/image/156254850/", "1932-September-8": "https://www.newspapers.com/image/156255177/", "1932-September-9": "https://www.newspapers.com/image/156255516/"}, "Allentown Morning Call": {"1935-December-1": "https://www.newspapers.com/image/274837908/", "1935-December-5": "https://www.newspapers.com/image/274841090/", "1935-December-7": "https://www.newspapers.com/image/274843604/", "1935-February-23": "https://www.newspapers.com/image/274693941/", "1944-July-16": "https://www.newspapers.com/image/279759759/", "1935-June-9": "https://www.newspapers.com/image/274700665/", "1935-March-23": "https://www.newspapers.com/image/274746212/", "1935-May-9": "https://www.newspapers.com/image/274797219/", "1935-November-24": "https://www.newspapers.com/image/274830714/", "1935-November-26": "https://www.newspapers.com/image/274832565/", "1935-November-27": "https://www.newspapers.com/image/274834157/", "1935-November-30": "https://www.newspapers.com/image/274837272/", "1935-October-25": "https://www.newspapers.com/image/274788607/"}, "Alton Illinois Evening Telegraph": {"1938-February-10": "https://www.newspapers.com/image/26078386/", "1938-February-26": "https://www.newspapers.com/image/26082309/", "1938-February-9": "https://www.newspapers.com/image/26078138/", "1934-June-19": "https://www.newspapers.com/image/17499950/", "1937-May-20": "https://www.newspapers.com/image/16326668/", "1937-May-21": "https://www.newspapers.com/image/16326700/", "1937-October-26": "https://www.newspapers.com/image/26083497/"}, "American Israelite": {"1937-April-1": "https://www.newspapers.com/paper/the-american-israelite/12328/", "1937-April-15": "https://www.newspapers.com/image/531472995/"}, "Arizona Republic": {"1936-January-24": "https://www.newspapers.com/image/117186945/", "1936-May-29": "https://www.newspapers.com/image/116955071/", "1935-October-16": "https://www.newspapers.com/image/117165946/"}, "Asbury Park Press": {"1934-August-3": "https://www.newspapers.com/image/143319918/", "1934-August-4": "https://www.newspapers.com/image/143319984/", "1937-February-5": "https://www.newspapers.com/image/143340934/", "1935-July-6": "https://www.newspapers.com/image/143939415/", "1935-July-3": "https://www.newspapers.com/image/143939245/", "1944-July-7": "https://www.newspapers.com/image/143462388/", "1934-June-20": "https://www.newspapers.com/image/143353539/", "1944-June-30": "https://www.newspapers.com/image/143455263/", "1934-September-7": "https://www.newspapers.com/image/143926327/"}, "Atlanta Constitution": {"1939-July-1": "https://www.newspapers.com/image/398141107/", "1939-July-2": "https://www.newspapers.com/image/398144133/", "1943-March-18": "https://www.newspapers.com/image/397952447/", "1943-March-19": "https://www.newspapers.com/image/397952991/"}, "Bakersfield Morning Echo": {"1926-September-3": "https://www.newspapers.com/image/610152999/", "1926-September-4": "https://www.newspapers.com/image/610153073/"}, "Bakersfield Californian": {"1937-February-6": "https://www.newspapers.com/image/1647944/"}, "Barnard Bulletin": {"1930-February-25": "https://www.newspapers.com/image/37829648/"}, "Benton Harbor News-Palladium": {"1934-August-26": "https://www.newspapers.com/image/364902631/"}, "Berwyn Life": {"1935-June-14": "https://www.newspapers.com/image/523669583/"}, "Chillicothe Gazette": {"1936-June-24": "https://www.newspapers.com/image/291460224/"}}, "newspaper_urls": {"Camden Courier-Post": "https://www.newspapers.com/paper/courier-post/3767/", "Minneapolis Star Tribune": "https://www.newspapers.com/paper/star-tribune/4474/", "Evening Review": "", "Hazleton Plain Speaker": "https://www.newspapers.com/paper/the-plain-speaker/2177/", "Indianapolis Star": "https://www.newspapers.com/paper/the-indianapolis-star/384/", "Brooklyn Daily Eagle": "https://www.newspapers.com/paper/the-brooklyn-daily-eagle/1890/", "**Unlisted QMH source 2": "", "Aiken Standard": "https://www.newspapers.com/paper/aiken-standard/290/", "Akron Beacon Journal": "https://www.newspapers.com/paper/the-akron-beacon-journal/4267/", "Albany Times-Union": "", "Albany Times-Union, date unknown": "", "Albuquerque Journal": "https://www.newspapers.com/paper/albuquerque-journal/971/", "Alexandria Town Talk": "", "Allentown Morning Call": "https://www.newspapers.com/paper/the-morning-call/5205/", "Alton Illinois Evening Telegraph": "https://www.newspapers.com/paper/alton-evening-telegraph/19/", "American Israelite": "https://www.newspapers.com/paper/the-american-israelite/12328/", "Amsterdam Evening Recorder": "", "Arizona Republic": "https://www.newspapers.com/paper/arizona-republic/208/", "Asbury Park Press": "https://www.newspapers.com/paper/asbury-park-press/3780/", "Atlanta Constitution": "https://www.newspapers.com/paper/the-atlanta-constitution/406/", "Bakersfield Morning Echo": "https://www.newspapers.com/paper/bakersfield-morning-echo/22050/", "Bakersfield Californian": "https://www.newspapers.com/paper/the-bakersfield-californian/8/", "Baldwinsville Gazette and Farmers Journal": "", "Baltimore Sun": "", "Barnard Bulletin": "https://www.newspapers.com/paper/barnard-bulletin/1168/", "Battle Creek Enquirer": "", "Benton Harbor News-Palladium": "https://www.newspapers.com/paper/the-news-palladium/662/", "Berwyn Life": "https://www.newspapers.com/paper/berwyn-life/12106/", "Billboard": "", "Billings Gazette": "", "Binghamton Press and Sun-Bulletin": "", "Binghamton Press": "", "Birmingham News": "", "Bismarck Tribune": "", "Bloomington Pantagraph": "", "Bluefield Daily Telegraph": "", "Boston Globe": "", "Bradford Evening Star and The Bradford Daily Record": "", "Brattleboro Reformer": "", "Bridgewater Courier-News": "", "Bristol Daily Courier": "", "Brooklyn Chat": "", "Brooklyn Citizen": "", "Brooklyn Home Talk the Item": "", "Brooklyn Standard Union": "", "Brooklyn Times Union": "", "Buffalo Courier-Express": "", "Buffalo Evening News": "", "Cache American": "", "Camden Morning Post": "", "Canandaigua Daily Messenger": "", "Casper Star-Tribune": "", "Central New Jersey Home News": "", "Charlotte Observer": "", "Chattanooga Daily Times": "", "Chattanooga News": "", "Chicago Defender": "", "Chico Enterprise": "", "Chico Record": "", "Chillicothe Constitution-Tribune": "", "Chillicothe Gazette": "https://www.newspapers.com/paper/chillicothe-gazette/3762/", "Cincinnati Enquirer": "", "Cleveland Call and Post": "", "Coast Advertiser": "", "Cohoes American": "", "Columbus Telegram": "", "Corpus Christi Caller-Times": "", "Cullman Tribune": "", "Daily News": "", "Daily Oklahoman": "", "Daily Record": "", "Daily Register": "", "Davenport Daily Times": "", "Davenport Quad-City Times": "", "Dayton Daily News": "", "Dayton Herald": ""}, "page_urls": {"Camden NJ Courier-Post": {"1943-July-19": {"8": "https://www.newspapers.com/image/480816100"}}, "Camden Courier-Post": {"1943-July-19": {"8": "https://www.newspapers.com/image/480816100"}, "1938-August-4": {"11": "https://www.newspapers.com/image/480354466"}, "1940-December-13": {"26": "https://www.newspapers.com/image/480446195", "30": "https://www.newspapers.com/image/480446232"}, "1933-November-20": {"10": "https://www.newspapers.com/image/479165238"}, "1930-October-25": {"4": "https://www.newspapers.com/image/479480661"}}, "Minneapolis Star Tribune": {"1949-August-12": {"4": "https://www.newspapers.com/image/180751297"}}, "Hazleton Plain Speaker": {"1935-November-23": {"14": "https://www.newspapers.com/image/98116292"}}, "Indianapolis Star": {"1930-April-9": {"9": "https://www.newspapers.com/image/104983031"}}, "Brooklyn Daily Eagle": {"1926-January-19": {"7": "https://www.newspapers.com/image/57560333"}, "1931-April-20": {"19": "https://www.newspapers.com/image/57366056"}, "1935-August-12": {"5": "https://www.newspapers.com/image/693805088"}, "1930-December-1": {"19": "https://www.newspapers.com/image/58061441"}, "1939-December-1": {"12": "https://www.newspapers.com/image/52769415"}, "1924-December-10": {"2": "https://www.newspapers.com/image/59858179"}, "1939-December-15": {"19": "https://www.newspapers.com/image/52776174"}, "1939-December-22": {"8": "https://www.newspapers.com/image/52778317"}, "1939-December-29": {"9": "https://www.newspapers.com/image/52780159"}, "1934-December-9": {"1": "https://www.newspapers.com/image/693865685"}, "1932-February-12": {"9": "https://www.newspapers.com/image/59867492"}, "1926-February-16": {"7": "https://www.newspapers.com/image/57556386"}, "1930-February-18": {"21": "https://www.newspapers.com/image/59908171"}, "1930-February-19": {"21": "https://www.newspapers.com/image/59908725"}, "1931-February-23": {"19": "https://www.newspapers.com/image/57577547"}, "1933-February-6": {"13": "https://www.newspapers.com/image/59864658"}, "1934-January-17": {"13": "https://www.newspapers.com/image/59991210"}, "1934-January-29": {"7": "https://www.newspapers.com/image/59998832"}, "1944-July-12": {"17": "https://www.newspapers.com/image/54498825"}, "1944-July-2": {"17": "https://www.newspapers.com/image/54497942"}, "1935-July-22": {"3": "https://www.newspapers.com/image/52620411"}, "1933-June-16": {"10": "https://www.newspapers.com/image/59988275"}, "1934-June-19": {"2": "https://www.newspapers.com/image/59990833"}, "1925-June-25": {"7": "https://www.newspapers.com/image/59907088"}, "1926-March-2": {"10": "https://www.newspapers.com/image/59844138"}, "1931-March-21": {"9": "https://www.newspapers.com/image/59841534"}, "1932-March-24": {"20": "https://www.newspapers.com/image/57401448"}, "1926-March-30": {"10": "https://www.newspapers.com/image/59850977"}, "1911-March-5": {"5": "https://www.newspapers.com/image/53888341"}, "1932-May-18": {"12": "https://www.newspapers.com/image/59971823"}, "1934-May-19": {"5": "https://www.newspapers.com/image/58260824"}, "1936-May-20": {"34": "https://www.newspapers.com/image/577442397"}, "1934-November-1": {"15": "https://www.newspapers.com/image/59971096"}, "1939-November-10": {"19": "https://www.newspapers.com/image/52759335"}, "1938-November-11": {"15": "https://www.newspapers.com/image/52621904"}, "1934-November-24": {"15": "https://www.newspapers.com/image/59992439"}, "1939-November-24": {"10": "https://www.newspapers.com/image/52767709"}, "1930-November-26": {"19": "https://www.newspapers.com/image/58229157"}, "1934-November-26": {"13": "https://www.newspapers.com/image/59994228"}, "1934-November-27": {"18": "https://www.newspapers.com/image/59994822"}, "1930-November-29": {"9": "https://www.newspapers.com/image/58229221"}, "1938-November-4": {"19": "https://www.newspapers.com/image/52617971"}, "1931-November-8": {"18": "https://www.newspapers.com/image/57388147"}, "1928-October-2": {"1": "https://www.newspapers.com/image/686514066", "2": "https://www.newspapers.com/image/57552475"}, "1941-October-24": {"13": "https://www.newspapers.com/image/52805537"}}, "Aiken Standard": {"1934-January-24": {"8": "https://www.newspapers.com/image/14191747"}}, "Akron Beacon Journal": {"1937-April-13": {"40": "https://www.newspapers.com/image/228680699"}, "1930-August-1": {"31": "https://www.newspapers.com/image/228836625"}, "1937-August-31": {"25": "https://www.newspapers.com/image/228732511"}, "1935-December-11": {"21": "https://www.newspapers.com/image/228473631"}, "1935-December-12": {"30": "https://www.newspapers.com/image/228474387"}, "1935-December-14": {"8": "https://www.newspapers.com/image/228475598"}, "1935-December-16": {"19": "https://www.newspapers.com/image/228476079"}, "1935-December-18": {"14": "https://www.newspapers.com/image/228476855"}, "1935-December-19": {"21": "https://www.newspapers.com/image/228477338"}, "1935-December-4": {"17": "https://www.newspapers.com/image/228469894"}, "1935-December-6": {"46": "https://www.newspapers.com/image/228471624"}, "1935-December-9": {"13": "https://www.newspapers.com/image/228472328"}, "1936-February-26": {"22": "https://www.newspapers.com/image/228592629"}, "1930-July-24": {"24": "https://www.newspapers.com/image/228838872"}, "1930-July-25": {"12": "https://www.newspapers.com/image/228839244"}, "1930-July-26": {"2": "https://www.newspapers.com/image/228839808"}, "1930-July-28": {"17": "https://www.newspapers.com/image/228840583"}, "1930-July-29": {"18": "https://www.newspapers.com/image/228841236"}, "1930-July-30": {"12": "https://www.newspapers.com/image/228841851"}, "1930-July-31": {"16": "https://www.newspapers.com/image/228842640"}, "1950-June-16": {"35": "https://www.newspapers.com/image/146521975"}, "1941-June-20": {"31": "https://www.newspapers.com/image/148379842"}, "1941-June-24": {"8": "https://www.newspapers.com/image/148381116"}, "1941-June-26": {"27": "https://www.newspapers.com/image/148381823"}, "1941-June-27": {"19": "https://www.newspapers.com/image/148382090"}, "1936-November-27": {"19": "https://www.newspapers.com/image/228723274"}, "1937-October-25": {"24": "https://www.newspapers.com/image/228714313"}, "1937-October-27": {"23": "https://www.newspapers.com/image/228714629"}, "1937-October-30": {"13": "https://www.newspapers.com/image/228715121"}, "1937-September-1": {"8": "https://www.newspapers.com/image/228655028"}, "1935-December-20": {"36": "https://www.newspapers.com/image/228477954", "29": "https://www.newspapers.com/image/228477874"}, "1935-December-21": {"1": "https://www.newspapers.com/image/228478175/", "21": "https://www.newspapers.com/image/228478372", "9": "https://www.newspapers.com/image/228478260"}, "1935-December-5": {"34": "https://www.newspapers.com/image/228470742"}, "1935-December-7": {"8": "https://www.newspapers.com/image/228471864"}}, "Albuquerque Journal": {"1932-April-23": {"5": "https://www.newspapers.com/image/156636150"}, "1935-August-29": {"10": "https://www.newspapers.com/image/156593456"}, "1932-September-10": {"3": "https://www.newspapers.com/image/156256009", "6": "https://www.newspapers.com/image/156256136"}, "1932-September-11": {"10": "https://www.newspapers.com/image/156256485"}, "1932-September-14": {"8": "https://www.newspapers.com/image/156257655"}, "1932-September-4": {"8": "https://www.newspapers.com/image/156254235"}, "1932-September-7": {"5": "https://www.newspapers.com/image/156255012", "8": "https://www.newspapers.com/image/156255149"}, "1932-September-8": {"8": "https://www.newspapers.com/image/156255487"}, "1932-September-9": {"10": "https://www.newspapers.com/image/156255893", "3": "https://www.newspapers.com/image/156255600"}}, "Allentown Morning Call": {"1935-December-1": {"15": "https://www.newspapers.com/image/274838378"}, "1935-December-5": {"15": "https://www.newspapers.com/image/274841577"}, "1935-December-7": {"13": "https://www.newspapers.com/image/274844212", "14": "https://www.newspapers.com/image/274844258"}, "1935-February-23": {"12": "https://www.newspapers.com/image/274694063"}, "1944-July-16": {"11": "https://www.newspapers.com/image/279760108"}, "1935-June-9": {"8": "https://www.newspapers.com/image/274700730"}, "1935-March-23": {"15": "https://www.newspapers.com/image/274746924"}, "1935-May-9": {"4": "https://www.newspapers.com/image/274797327"}, "1935-November-24": {"15": "https://www.newspapers.com/image/274831101"}, "1935-November-26": {"19": "https://www.newspapers.com/image/274833324"}, "1935-November-27": {"10": "https://www.newspapers.com/image/274834496"}, "1935-November-30": {"13": "https://www.newspapers.com/image/274837666"}, "1935-October-25": {"27": "https://www.newspapers.com/image/274789242"}}, "Alton Illinois Evening Telegraph": {"1938-February-10": {"17": "https://www.newspapers.com/image/26078630"}, "1938-February-26": {"11": "https://www.newspapers.com/image/26082470"}, "1938-February-9": {"11": "https://www.newspapers.com/image/26078309"}, "1934-June-19": {"1": "https://www.newspapers.com/image/17499950/"}, "1937-May-20": {"29": "https://www.newspapers.com/image/16326696"}, "1937-May-21": {"15": "https://www.newspapers.com/image/16326714"}, "1937-October-26": {"5": "https://www.newspapers.com/image/26083575"}}, "Arizona Republic": {"1936-January-24": {"4": "https://www.newspapers.com/image/117186988"}, "1936-May-29": {"11": "https://www.newspapers.com/image/116955128"}, "1935-October-16": {"13": "https://www.newspapers.com/image/117166064"}}, "Asbury Park Press": {"1934-August-3": {"19": "https://www.newspapers.com/image/143319972"}, "1934-August-4": {"4": "https://www.newspapers.com/image/143319993"}, "1937-February-5": {"3": "https://www.newspapers.com/image/143340946"}, "1935-July-3": {"7": "https://www.newspapers.com/image/143939270"}, "1935-July-6": {"7": "https://www.newspapers.com/image/143939440"}, "1944-July-7": {"16": "https://www.newspapers.com/image/143462432"}, "1934-June-20": {"25": "https://www.newspapers.com/image/143353765"}, "1944-June-30": {"8": "https://www.newspapers.com/image/143455276"}, "1934-September-7": {"20": "https://www.newspapers.com/image/143926573"}}, "Atlanta Constitution": {"1939-July-1": {"7": "https://www.newspapers.com/image/398141666"}, "1939-July-2": {"6": "https://www.newspapers.com/image/398145586"}, "1943-March-18": {"10": "https://www.newspapers.com/image/397952582"}, "1943-March-19": {"18": "https://www.newspapers.com/image/397953276"}}, "Bakersfield Morning Echo": {"1926-September-3": {"4": "https://www.newspapers.com/image/610153026"}, "1926-September-4": {"5": "https://www.newspapers.com/image/610153113"}}, "Bakersfield Californian": {"1937-February-6": {"8": "https://www.newspapers.com/image/1648053"}}, "Barnard Bulletin": {"1930-February-25": {"2": "https://www.newspapers.com/image/37829649"}}, "Benton Harbor News-Palladium": {"1934-August-26": {"2": "https://www.newspapers.com/image/364902662"}}, "Berwyn Life": {"1935-June-14": {"8": "https://www.newspapers.com/image/523669612"}}, "Chillicothe Gazette": {"1936-June-24": {"5": "https://www.newspapers.com/image/291460345"}}}, "ambiguous": ["Alexandria Town Talk", "Amsterdam Evening Recorder", "Baltimore Sun", "Battle Creek Enquirer", "Billings Gazette", "Binghamton Press and Sun-Bulletin", "Binghamton Press", "Birmingham News", "Bismarck Tribune", "Bloomington Pantagraph", "Bluefield Daily Telegraph", "Boston Globe", "Bradford Evening Star and The Bradford Daily Record", "Brattleboro Reformer", "Bridgewater Courier-News", "Bristol Daily Courier", "Brooklyn Chat", "Brooklyn Citizen", "Brooklyn Home Talk the Item", "Brooklyn Standard Union", "Brooklyn Times Union", "Buffalo Courier-Express", "Buffalo Evening News", "Cache American", "Camden Morning Post", "Canandaigua Daily Messenger", "Casper Star-Tribune", "Central New Jersey Home News", "Charlotte Observer", "Chattanooga Daily Times", "Chattanooga News", "Chicago Defender", "Chico Enterprise", "Chico Record", "Chillicothe Constitution-Tribune", "Cincinnati Enquirer", "Cleveland Call and Post", "Coast Advertiser", "Cohoes American", "Columbus Telegram", "Corpus Christi Caller-Times", "Cullman Tribune", "Daily News", "Daily Oklahoman", "Daily Record", "Daily Register", "Davenport Daily Times", "Davenport Quad-City Times", "Dayton Daily News", "Dayton Herald"], "no_link": {}}